{
"dashboard":
{
  "title": "C2Live",	
  "annotations": {
    "list": [
      {
        "builtIn": 1,
        "datasource": {
          "type": "grafana",
          "uid": "-- Grafana --"
        },
        "enable": true,
        "hide": true,
        "iconColor": "rgba(0, 211, 255, 1)",
        "name": "Annotations & Alerts",
        "type": "dashboard"
      }
    ]
  },
  "editable": true,
  "fiscalYearStartMonth": 0,
  "graphTooltip": 0,
  "id": null,
  "links": [],
  "liveNow": false,
  "panels": [
    {
      "datasource": {
        "type": "elasticsearch",
        "uid": "e4994ccf-a285-445f-be54-8c393490c47f",
	"access": "server"
      },
      "fieldConfig": {
        "defaults": {
          "color": {
            "mode": "thresholds"
          },
          "custom": {
            "hideFrom": {
              "legend": false,
              "tooltip": false,
              "viz": false
            }
          },
          "mappings": [],
          "thresholds": {
            "mode": "absolute",
            "steps": [
              {
                "color": "green",
                "value": null
              },
              {
                "color": "red",
                "value": 80
              }
            ]
          }
        },
        "overrides": []
      },
      "gridPos": {
        "h": 16,
        "w": 12,
        "x": 0,
        "y": 0
      },
      "id": 4,
      "options": {
        "basemap": {
          "config": {},
          "name": "Layer 0",
          "type": "default"
        },
        "controls": {
          "mouseWheelZoom": true,
          "showAttribution": true,
          "showDebug": false,
          "showMeasure": false,
          "showScale": false,
          "showZoom": true
        },
        "layers": [
          {
            "config": {
              "blur": 15,
              "radius": 5,
              "weight": {
                "fixed": 1,
                "max": 1,
                "min": 0
              }
            },
            "location": {
              "latitude": "geoip.location.lat",
              "longitude": "geoip.location.lon",
              "mode": "coords"
            },
            "name": "Layer 1",
            "tooltip": true,
            "type": "heatmap"
          }
        ],
        "tooltip": {
          "mode": "details"
        },
        "view": {
          "allLayers": true,
          "id": "europe",
          "lat": 46,
          "lon": 14,
          "zoom": 3
        }
      },
      "pluginVersion": "10.0.3",
      "targets": [
        {
          "alias": "",
          "bucketAggs": [],
          "datasource": {
            "type": "elasticsearch",
            "uid": "e4994ccf-a285-445f-be54-8c393490c47f"
          },
          "metrics": [
            {
              "id": "1",
              "settings": {
                "size": "500"
              },
              "type": "raw_data"
            }
          ],
          "query": "framework.keyword:$variable_framework AND geoip.country_name.keyword:$variable_country",
          "refId": "A",
          "timeField": "@timestamp"
        }
      ],
      "title": "$variable_country country $variable_framework framework repartition",
      "transparent": true,
      "type": "geomap"
    },
    {
      "datasource": {
        "type": "elasticsearch",
        "uid": "e4994ccf-a285-445f-be54-8c393490c47f"
      },
      "fieldConfig": {
        "defaults": {
          "color": {
            "mode": "palette-classic"
          },
          "custom": {
            "axisCenteredZero": false,
            "axisColorMode": "text",
            "axisLabel": "",
            "axisPlacement": "auto",
            "fillOpacity": 80,
            "gradientMode": "none",
            "hideFrom": {
              "legend": false,
              "tooltip": false,
              "viz": false
            },
            "lineWidth": 1,
            "scaleDistribution": {
              "type": "linear"
            },
            "thresholdsStyle": {
              "mode": "off"
            }
          },
          "mappings": [],
          "thresholds": {
            "mode": "absolute",
            "steps": [
              {
                "color": "green",
                "value": null
              },
              {
                "color": "red",
                "value": 80
              }
            ]
          }
        },
        "overrides": []
      },
      "gridPos": {
        "h": 8,
        "w": 12,
        "x": 12,
        "y": 0
      },
      "id": 3,
      "maxDataPoints": 1,
      "options": {
        "barRadius": 0.1,
        "barWidth": 0.82,
        "fullHighlight": false,
        "groupWidth": 0.7,
        "legend": {
          "calcs": [],
          "displayMode": "list",
          "placement": "bottom",
          "showLegend": true
        },
        "orientation": "horizontal",
        "showValue": "auto",
        "stacking": "none",
        "tooltip": {
          "mode": "single",
          "sort": "none"
        },
        "xTickLabelRotation": 0,
        "xTickLabelSpacing": 0
      },
      "pluginVersion": "10.0.3",
      "targets": [
        {
          "alias": "",
          "bucketAggs": [
            {
              "field": "framework.keyword",
              "id": "2",
              "settings": {
                "min_doc_count": "1",
                "order": "desc",
                "orderBy": "_count",
                "size": "10"
              },
              "type": "terms"
            }
          ],
          "datasource": {
            "type": "elasticsearch",
            "uid": "e4994ccf-a285-445f-be54-8c393490c47f"
          },
          "metrics": [
            {
              "field": "ip.keyword",
              "id": "1",
              "type": "cardinality"
            }
          ],
          "query": "framework.keyword:$variable_framework AND geoip.country_name.keyword:$variable_country",
          "refId": "A",
          "timeField": "@timestamp"
        }
      ],
      "title": "$variable_country country $variable_framework Framework repartition",
      "transparent": true,
      "type": "barchart"
    },
    {
      "datasource": {
        "type": "elasticsearch",
        "uid": "e4994ccf-a285-445f-be54-8c393490c47f"
      },
      "fieldConfig": {
        "defaults": {
          "color": {
            "mode": "palette-classic"
          },
          "custom": {
            "hideFrom": {
              "legend": false,
              "tooltip": false,
              "viz": false
            }
          },
          "mappings": []
        },
        "overrides": []
      },
      "gridPos": {
        "h": 8,
        "w": 12,
        "x": 12,
        "y": 8
      },
      "id": 5,
      "maxDataPoints": 1,
      "options": {
        "displayLabels": [
          "name"
        ],
        "legend": {
          "displayMode": "list",
          "placement": "right",
          "showLegend": true,
          "values": [
            "percent"
          ]
        },
        "pieType": "donut",
        "reduceOptions": {
          "calcs": [
            "lastNotNull"
          ],
          "fields": "",
          "values": true
        },
        "tooltip": {
          "mode": "single",
          "sort": "none"
        }
      },
      "pluginVersion": "10.0.3",
      "targets": [
        {
          "alias": "",
          "bucketAggs": [
            {
              "field": "framework.keyword",
              "id": "2",
              "settings": {
                "min_doc_count": "1",
                "order": "desc",
                "orderBy": "_count",
                "size": "0"
              },
              "type": "terms"
            }
          ],
          "datasource": {
            "type": "elasticsearch",
            "uid": "e4994ccf-a285-445f-be54-8c393490c47f"
          },
          "metrics": [
            {
              "field": "ip.keyword",
              "id": "1",
              "type": "cardinality"
            }
          ],
          "query": "framework.keyword:$variable_framework AND geoip.country_name.keyword:$variable_country",
          "refId": "A",
          "timeField": "@timestamp"
        }
      ],
      "title": "$variable_country country Framework repartition",
      "transparent": true,
      "type": "piechart"
    },
    {
      "datasource": {
        "type": "elasticsearch",
        "uid": "e4994ccf-a285-445f-be54-8c393490c47f"
      },
      "fieldConfig": {
        "defaults": {
          "color": {
            "mode": "palette-classic"
          },
          "custom": {
            "axisCenteredZero": false,
            "axisColorMode": "text",
            "axisLabel": "",
            "axisPlacement": "auto",
            "fillOpacity": 80,
            "gradientMode": "none",
            "hideFrom": {
              "legend": false,
              "tooltip": false,
              "viz": false
            },
            "lineWidth": 1,
            "scaleDistribution": {
              "type": "linear"
            },
            "thresholdsStyle": {
              "mode": "off"
            }
          },
          "mappings": [],
          "thresholds": {
            "mode": "absolute",
            "steps": [
              {
                "color": "green",
                "value": null
              },
              {
                "color": "red",
                "value": 80
              }
            ]
          }
        },
        "overrides": []
      },
      "gridPos": {
        "h": 8,
        "w": 12,
        "x": 0,
        "y": 16
      },
      "id": 6,
      "maxDataPoints": 1,
      "options": {
        "barRadius": 0.1,
        "barWidth": 0.82,
        "fullHighlight": false,
        "groupWidth": 0.7,
        "legend": {
          "calcs": [],
          "displayMode": "list",
          "placement": "bottom",
          "showLegend": true
        },
        "orientation": "horizontal",
        "showValue": "auto",
        "stacking": "none",
        "tooltip": {
          "mode": "single",
          "sort": "none"
        },
        "xTickLabelRotation": 0,
        "xTickLabelSpacing": 0
      },
      "pluginVersion": "10.0.3",
      "targets": [
        {
          "alias": "",
          "bucketAggs": [
            {
              "field": "geoip.country_name.keyword",
              "id": "2",
              "settings": {
                "min_doc_count": "1",
                "order": "desc",
                "orderBy": "_count",
                "size": "10"
              },
              "type": "terms"
            }
          ],
          "datasource": {
            "type": "elasticsearch",
            "uid": "e4994ccf-a285-445f-be54-8c393490c47f"
          },
          "metrics": [
            {
              "field": "ip.keyword",
              "id": "1",
              "type": "cardinality"
            }
          ],
          "query": "framework.keyword:$variable_framework AND geoip.country_name.keyword:$variable_country",
          "refId": "A",
          "timeField": "@timestamp"
        }
      ],
      "title": "Top 10 : Country $variable_framework Framework",
      "transparent": true,
      "type": "barchart"
    },
    {
      "datasource": {
        "type": "elasticsearch",
        "uid": "e4994ccf-a285-445f-be54-8c393490c47f"
      },
      "fieldConfig": {
        "defaults": {
          "color": {
            "mode": "thresholds"
          },
          "custom": {
            "align": "auto",
            "cellOptions": {
              "type": "auto"
            },
            "inspect": false
          },
          "mappings": [],
          "thresholds": {
            "mode": "absolute",
            "steps": [
              {
                "color": "green",
                "value": null
              },
              {
                "color": "red",
                "value": 80
              }
            ]
          }
        },
        "overrides": []
      },
      "gridPos": {
        "h": 8,
        "w": 12,
        "x": 12,
        "y": 16
      },
      "id": 7,
      "maxDataPoints": 1,
      "options": {
        "cellHeight": "sm",
        "footer": {
          "countRows": false,
          "fields": "",
          "reducer": [
            "sum"
          ],
          "show": false
        },
        "showHeader": true
      },
      "pluginVersion": "10.0.3",
      "targets": [
        {
          "alias": "",
          "bucketAggs": [],
          "datasource": {
            "type": "elasticsearch",
            "uid": "e4994ccf-a285-445f-be54-8c393490c47f"
          },
          "metrics": [
            {
              "id": "1",
              "settings": {
                "size": "500"
              },
              "type": "raw_data"
            }
          ],
          "query": "framework.keyword:$variable_framework AND geoip.country_name.keyword:$variable_country",
          "refId": "A",
          "timeField": "@timestamp"
        }
      ],
      "title": "$variable_framework framework IP address",
      "transformations": [
        {
          "id": "filterFieldsByName",
          "options": {
            "include": {
              "names": [
                "ip"
              ]
            }
          }
        }
      ],
      "transparent": true,
      "type": "table"
    },
    {
      "datasource": {
        "type": "elasticsearch",
        "uid": "baf72e2b-0d75-441b-be7b-3ccfa477c95a"
      },
      "gridPos": {
        "h": 3,
        "w": 11,
        "x": 7,
        "y": 24
      },
      "id": 8,
      "options": {
        "code": {
          "language": "plaintext",
          "showLineNumbers": false,
          "showMiniMap": false
        },
        "content": "  Provided by [@Y_NeXRo](https://twitter.com/Y_NeXRo) and [@ikuroNoriiwa](https://twitter.com/ikuroNoriiwa)  \n",
        "mode": "markdown"
      },
      "pluginVersion": "10.0.3",
      "targets": [
        {
          "alias": "",
          "bucketAggs": [
            {
              "field": "@timestamp",
              "id": "2",
              "settings": {
                "interval": "auto"
              },
              "type": "date_histogram"
            }
          ],
          "datasource": {
            "type": "elasticsearch",
            "uid": "baf72e2b-0d75-441b-be7b-3ccfa477c95a"
          },
          "metrics": [
            {
              "id": "1",
              "type": "count"
            }
          ],
          "query": "",
          "refId": "A",
          "timeField": "@timestamp"
        }
      ],
      "transparent": true,
      "type": "text"
    }
  ],
  "refresh": false,
  "schemaVersion": 38,
  "style": "dark",
  "tags": [],
  "templating": {
    "list": [
      {
        "current": {
          "selected": true,
          "text": "All",
          "value": "$__all"
        },
        "datasource": {
          "type": "elasticsearch",
          "uid": "e4994ccf-a285-445f-be54-8c393490c47f",
	  "access": "server"
        },
        "definition": "{\"find\": \"terms\", \"field\": \"framework.keyword\", \"size\": 1000 }",
        "hide": 0,
        "includeAll": true,
        "label": "framework",
        "multi": false,
        "name": "variable_framework",
        "options": [],
        "query": "{\"find\": \"terms\", \"field\": \"framework.keyword\", \"size\": 1000 }",
        "refresh": 2,
        "regex": "",
        "skipUrlSync": false,
        "sort": 1,
        "type": "query"
      },
      {
        "current": {
          "selected": true,
          "text": "All",
          "value": "$__all"
        },
        "datasource": {
          "type": "elasticsearch",
          "uid": "e4994ccf-a285-445f-be54-8c393490c47f",
	  "access": "server"
        },
        "definition": "{\"find\": \"terms\", \"field\": \"geoip.country_name.keyword\", \"size\": 1000 }",
        "hide": 0,
        "includeAll": true,
        "label": "country",
        "multi": false,
        "name": "variable_country",
        "options": [],
        "query": "{\"find\": \"terms\", \"field\": \"geoip.country_name.keyword\", \"size\": 1000 }",
        "refresh": 2,
        "regex": "",
        "skipUrlSync": false,
        "sort": 1,
        "type": "query"
      }
    ]
  },
  "time": {
    "from": "now-d",
    "to": "now"
  },
  "timepicker": {
    "refresh_intervals": [
      "1d"
    ]
  },
  "timezone": "",
  "title": "C2Live",
  "uid": "c396b477-7a2b-483b-b0c1-8cc6711e2c6d",
  "version": 3,
  "weekStart": ""
},
"folderId": 0,
"overwrite": true
}
